<?xml version="1.0" encoding="utf-8" ?>
<dwsync>
<file name="Core.php" server="C:/xampp/htdocs/inventiomax8/" local="131829958288671975" remote="131829958280000000" Dst="0" />
<file name="View.php" server="C:/xampp/htdocs/inventiomax8/" local="131829958291062248" remote="131829958290000000" Dst="0" />
<file name="Module.php" server="C:/xampp/htdocs/inventiomax8/" local="131829958288701893" remote="131829958280000000" Dst="0" />
<file name="Database.php" server="C:/xampp/htdocs/inventiomax8/" local="131829958288681949" remote="131829958280000000" Dst="0" />
<file name="Executor.php" server="C:/xampp/htdocs/inventiomax8/" local="131829958288681949" remote="131829958280000000" Dst="0" />
<file name="Lb.php" server="C:/xampp/htdocs/inventiomax8/" local="131829958288691908" remote="131829958280000000" Dst="0" />
<file name="Model.php" server="C:/xampp/htdocs/inventiomax8/" local="131829958288701893" remote="131829958280000000" Dst="0" />
<file name="Bootload.php" server="C:/xampp/htdocs/inventiomax8/" local="131829958288671975" remote="131829958280000000" Dst="0" />
<file name="Action.php" server="C:/xampp/htdocs/inventiomax8/" local="131829958288661994" remote="131829958280000000" Dst="0" />
<file name="class.upload.php" server="C:/xampp/htdocs/inventiomax8/" local="131829958291102081" remote="131829958290000000" Dst="0" />
<file name="class.phpmailer.php" server="C:/xampp/htdocs/inventiomax8/" local="131829958291071872" remote="131829958290000000" Dst="0" />
<file name="class.smtp.php" server="C:/xampp/htdocs/inventiomax8/" local="131829958291082090" remote="131829958290000000" Dst="0" />
<file name="class.pop3.php" server="C:/xampp/htdocs/inventiomax8/" local="131829958291071872" remote="131829958290000000" Dst="0" />
</dwsync>